AUTHORS.rst
CONTRIBUTING.rst
HISTORY.rst
LICENSE
MANIFEST.in
README.rst
setup.cfg
setup.py
docs/Makefile
docs/authors.rst
docs/conf.py
docs/contributing.rst
docs/history.rst
docs/index.rst
docs/installation.rst
docs/make.bat
docs/readme.rst
docs/usage.rst
eventbrite/__init__.py
eventbrite/_version.py
eventbrite/access_methods.py
eventbrite/apiv3_url_mapping.json
eventbrite/client.py
eventbrite/compat.py
eventbrite/decorators.py
eventbrite/exceptions.py
eventbrite/models.py
eventbrite/utils.py
tests/__init__.py
tests/base.py
tests/test_models.py
tests/test_utils.py
tests/integration/__init__.py
tests/integration/test_client.py
workthing.egg-info/PKG-INFO
workthing.egg-info/SOURCES.txt
workthing.egg-info/dependency_links.txt
workthing.egg-info/not-zip-safe
workthing.egg-info/requires.txt
workthing.egg-info/top_level.txt